graph_topper/__init__.py
graph_topper/topper.py
graph_topper/utils.py
graph_topper-0.1.0.dist-info/licenses/LICENSE
graph_topper-0.1.0.dist-info/METADATA
graph_topper-0.1.0.dist-info/WHEEL
graph_topper-0.1.0.dist-info/top_level.txt
graph_topper-0.1.0.dist-info/RECORD
