Metadata-Version: 2.4
Name: graph-topper
Version: 0.1.0
Summary: `graph-topper` is a small extension to the `lang-graph` library that allows for graph definitions via decorators, bringing flow-control and logic to one place.
Author-email: Jens Kaiser <jens-kaiser@online.de>
License-Expression: MIT
Requires-Python: >=3.9
License-File: LICENSE
Requires-Dist: langgraph>=0.1.2
Dynamic: license-file
